wmectrl/__init__.py
wmectrl/command_line_options.py
wmectrl/constants.py
wmectrl/main.py
wmectrl/requires.py
wmectrl/screen.py
wmectrl/window.py
wmectrl/wmectrl.py
wmectrl/workspace.py
wmectrl-0.2.3.dist-info/licenses/LICENSE
wmectrl-0.2.3.dist-info/METADATA
wmectrl-0.2.3.dist-info/WHEEL
wmectrl-0.2.3.dist-info/entry_points.txt
wmectrl-0.2.3.dist-info/top_level.txt
wmectrl-0.2.3.dist-info/RECORD
