Metadata-Version: 2.4
Name: wmectrl
Version: 0.2.3
Summary: An enhanced window manager control
Home-page: http://www.muflone.com/wmectrl/
Author: Fabio Castelli
Author-email: muflone@muflone.com
License: GPL-3.0-or-later
Classifier: Development Status :: 1 - Planning
Classifier: Intended Audience :: Developers
Classifier: Operating System :: OS Independent
Classifier: Programming Language :: Python :: 3
Classifier: Programming Language :: Python :: 3.9
Classifier: Programming Language :: Python :: 3.10
Classifier: Programming Language :: Python :: 3.11
Classifier: Programming Language :: Python :: 3.12
Classifier: Programming Language :: Python :: 3.13
License-File: LICENSE
Requires-Dist: PyGObject~=3.48
Dynamic: license-file
